[{"fK_iNhanvienID":"604e50f39c8b96835ba9ff97","tThoigianVaolamSang":"07:38:53","tThoigianNghiSang":"12:08:07","tThoigianVaolamChieu":"13:40:49","tThoigianNghiChieu":"15:04:00","tThoigianVaolamToi":null,"tThoigianNghiToi":null,"dNgayChamcong":"02-12-2021"},{"fK_iNhanvienID":"60555964d242573c7742cf34","tThoigianVaolamSang":"07:37:24","tThoigianNghiSang":"12:04:30","tThoigianVaolamChieu":"14:16:06","tThoigianNghiChieu":"15:09:42","tThoigianVaolamToi":null,"tThoigianNghiToi":null,"dNgayChamcong":"02-12-2021"},{"fK_iNhanvienID":"605569230fe553fa0f49c29e","tThoigianVaolamSang":"07:32:01","tThoigianNghiSang":"12:07:19","tThoigianVaolamChieu":"13:25:09","tThoigianNghiChieu":"15:06:15","tThoigianVaolamToi":null,"tThoigianNghiToi":null,"dNgayChamcong":"02-12-2021"}]