[{"fK_iNhanvienID":"604e50f39c8b96835ba9ff97","tThoigianVaolamSang":"07:56:18","tThoigianNghiSang":"12:01:36","tThoigianVaolamChieu":"14:32:39","tThoigianNghiChieu":"17:33:03","tThoigianVaolamToi":null,"tThoigianNghiToi":null,"dNgayChamcong":"16-08-2018"},{"fK_iNhanvienID":"605ea67db4c6befeb4b73e9d","tThoigianVaolamSang":"07:43:24","tThoigianNghiSang":"12:07:53","tThoigianVaolamChieu":"13:31:32","tThoigianNghiChieu":"17:36:24","tThoigianVaolamToi":null,"tThoigianNghiToi":null,"dNgayChamcong":"16-08-2018"},{"fK_iNhanvienID":"605ed0c04f8b3c1689f19b88","tThoigianVaolamSang":"08:06:14","tThoigianNghiSang":"12:07:41","tThoigianVaolamChieu":"13:41:43","tThoigianNghiChieu":"17:38:11","tThoigianVaolamToi":null,"tThoigianNghiToi":null,"dNgayChamcong":"16-08-2018"},{"fK_iNhanvienID":"605ed1094f8b3c1689f19b8a","tThoigianVaolamSang":"08:04:13","tThoigianNghiSang":"12:10:02","tThoigianVaolamChieu":"13:10:28","tThoigianNghiChieu":"17:38:06","tThoigianVaolamToi":null,"tThoigianNghiToi":null,"dNgayChamcong":"16-08-2018"},{"fK_iNhanvienID":"605ed1774f8b3c1689f19b8c","tThoigianVaolamSang":"07:31:02","tThoigianNghiSang":"12:00:47","tThoigianVaolamChieu":"13:28:33","tThoigianNghiChieu":"17:32:57","tThoigianVaolamToi":null,"tThoigianNghiToi":null,"dNgayChamcong":"16-08-2018"},{"fK_iNhanvienID":"605ed3534f8b3c1689f19b8e","tThoigianVaolamSang":"07:52:59","tThoigianNghiSang":"12:04:44","tThoigianVaolamChieu":"13:37:25","tThoigianNghiChieu":"17:30:37","tThoigianVaolamToi":null,"tThoigianNghiToi":null,"dNgayChamcong":"16-08-2018"},{"fK_iNhanvienID":"605ed4ba4f8b3c1689f19b90","tThoigianVaolamSang":"08:18:31","tThoigianNghiSang":"12:08:17","tThoigianVaolamChieu":"13:59:06","tThoigianNghiChieu":"17:37:57","tThoigianVaolamToi":null,"tThoigianNghiToi":null,"dNgayChamcong":"16-08-2018"},{"fK_iNhanvienID":"605ed6144f8b3c1689f19b92","tThoigianVaolamSang":"08:13:27","tThoigianNghiSang":"12:09:14","tThoigianVaolamChieu":"13:59:43","tThoigianNghiChieu":"17:38:24","tThoigianVaolamToi":null,"tThoigianNghiToi":null,"dNgayChamcong":"16-08-2018"},{"fK_iNhanvienID":"605ed6684f8b3c1689f19b94","tThoigianVaolamSang":"07:30:40","tThoigianNghiSang":"12:04:33","tThoigianVaolamChieu":"13:25:47","tThoigianNghiChieu":"17:35:02","tThoigianVaolamToi":null,"tThoigianNghiToi":null,"dNgayChamcong":"16-08-2018"},{"fK_iNhanvienID":"605ed6ad4f8b3c1689f19b96","tThoigianVaolamSang":"08:05:45","tThoigianNghiSang":"12:07:35","tThoigianVaolamChieu":"13:01:46","tThoigianNghiChieu":"17:39:16","tThoigianVaolamToi":null,"tThoigianNghiToi":null,"dNgayChamcong":"16-08-2018"},{"fK_iNhanvienID":"605ed7504f8b3c1689f19b98","tThoigianVaolamSang":"08:25:00","tThoigianNghiSang":"12:09:25","tThoigianVaolamChieu":"13:41:32","tThoigianNghiChieu":"17:34:57","tThoigianVaolamToi":null,"tThoigianNghiToi":null,"dNgayChamcong":"16-08-2018"},{"fK_iNhanvienID":"605ed80f4f8b3c1689f19b9a","tThoigianVaolamSang":"08:03:13","tThoigianNghiSang":"12:09:16","tThoigianVaolamChieu":"13:36:22","tThoigianNghiChieu":"17:33:37","tThoigianVaolamToi":null,"tThoigianNghiToi":null,"dNgayChamcong":"16-08-2018"},{"fK_iNhanvienID":"605ed9484f8b3c1689f19b9d","tThoigianVaolamSang":"08:16:47","tThoigianNghiSang":"12:08:54","tThoigianVaolamChieu":"13:49:33","tThoigianNghiChieu":"17:39:42","tThoigianVaolamToi":null,"tThoigianNghiToi":null,"dNgayChamcong":"16-08-2018"},{"fK_iNhanvienID":"605ed9884f8b3c1689f19b9f","tThoigianVaolamSang":"07:33:20","tThoigianNghiSang":"12:01:48","tThoigianVaolamChieu":"13:33:06","tThoigianNghiChieu":"17:33:15","tThoigianVaolamToi":null,"tThoigianNghiToi":null,"dNgayChamcong":"16-08-2018"},{"fK_iNhanvienID":"605eda0e4f8b3c1689f19ba1","tThoigianVaolamSang":"07:48:37","tThoigianNghiSang":"12:01:52","tThoigianVaolamChieu":"13:54:04","tThoigianNghiChieu":"17:37:29","tThoigianVaolamToi":null,"tThoigianNghiToi":null,"dNgayChamcong":"16-08-2018"},{"fK_iNhanvienID":"605eda814f8b3c1689f19ba3","tThoigianVaolamSang":"07:31:38","tThoigianNghiSang":"12:03:05","tThoigianVaolamChieu":"13:02:41","tThoigianNghiChieu":"17:37:54","tThoigianVaolamToi":null,"tThoigianNghiToi":null,"dNgayChamcong":"16-08-2018"},{"fK_iNhanvienID":"605edb09bd0d3a60ae2846ba","tThoigianVaolamSang":"07:47:15","tThoigianNghiSang":"12:02:19","tThoigianVaolamChieu":"13:06:35","tThoigianNghiChieu":"17:36:35","tThoigianVaolamToi":null,"tThoigianNghiToi":null,"dNgayChamcong":"16-08-2018"},{"fK_iNhanvienID":"605edb4cbd0d3a60ae2846bc","tThoigianVaolamSang":"07:36:19","tThoigianNghiSang":"12:02:38","tThoigianVaolamChieu":"13:44:44","tThoigianNghiChieu":"17:30:18","tThoigianVaolamToi":null,"tThoigianNghiToi":null,"dNgayChamcong":"16-08-2018"},{"fK_iNhanvienID":"605edb94bd0d3a60ae2846be","tThoigianVaolamSang":"07:30:08","tThoigianNghiSang":"12:03:48","tThoigianVaolamChieu":"13:29:48","tThoigianNghiChieu":"17:36:49","tThoigianVaolamToi":null,"tThoigianNghiToi":null,"dNgayChamcong":"16-08-2018"},{"fK_iNhanvienID":"605edbd1bd0d3a60ae2846c0","tThoigianVaolamSang":"07:49:37","tThoigianNghiSang":"12:08:23","tThoigianVaolamChieu":"13:04:20","tThoigianNghiChieu":"17:39:07","tThoigianVaolamToi":null,"tThoigianNghiToi":null,"dNgayChamcong":"16-08-2018"}]