[{"fK_iNhanvienID":"604e50f39c8b96835ba9ff97","tThoigianVaolamSang":"08:56:15","tThoigianNghiSang":"12:01:41","tThoigianVaolamChieu":"13:20:12","tThoigianNghiChieu":"15:00:41","tThoigianVaolamToi":null,"tThoigianNghiToi":null,"dNgayChamcong":"28-07-2021"},{"fK_iNhanvienID":"60555964d242573c7742cf34","tThoigianVaolamSang":"08:06:31","tThoigianNghiSang":"12:00:28","tThoigianVaolamChieu":"13:08:40","tThoigianNghiChieu":"15:01:23","tThoigianVaolamToi":null,"tThoigianNghiToi":null,"dNgayChamcong":"28-07-2021"},{"fK_iNhanvienID":"605569230fe553fa0f49c29e","tThoigianVaolamSang":"08:29:59","tThoigianNghiSang":"12:06:40","tThoigianVaolamChieu":"13:34:56","tThoigianNghiChieu":"15:06:29","tThoigianVaolamToi":null,"tThoigianNghiToi":null,"dNgayChamcong":"28-07-2021"}]