[{"fK_iNhanvienID":"604e50f39c8b96835ba9ff97","tThoigianVaolamSang":"08:23:52","tThoigianNghiSang":"12:01:28","tThoigianVaolamChieu":"13:40:18","tThoigianNghiChieu":"15:02:58","tThoigianVaolamToi":null,"tThoigianNghiToi":null,"dNgayChamcong":"04-03-2019"},{"fK_iNhanvienID":"60555964d242573c7742cf34","tThoigianVaolamSang":"08:06:48","tThoigianNghiSang":"12:02:37","tThoigianVaolamChieu":"14:03:35","tThoigianNghiChieu":"15:04:09","tThoigianVaolamToi":null,"tThoigianNghiToi":null,"dNgayChamcong":"04-03-2019"},{"fK_iNhanvienID":"605569230fe553fa0f49c29e","tThoigianVaolamSang":"07:02:08","tThoigianNghiSang":"12:04:43","tThoigianVaolamChieu":"14:54:33","tThoigianNghiChieu":"15:04:39","tThoigianVaolamToi":null,"tThoigianNghiToi":null,"dNgayChamcong":"04-03-2019"}]