[{"fK_iNhanvienID":1,"tThoigianVaolamSang":"07:31:01","tThoigianNghiSang":"12:04:16","tThoigianVaolamChieu":"14:06:12","tThoigianNghiChieu":"15:04:37","tThoigianVaolamToi":null,"tThoigianNghiToi":null,"dNgayChamcong":"10-11-2020"},{"fK_iNhanvienID":2,"tThoigianVaolamSang":"08:43:16","tThoigianNghiSang":"12:02:42","tThoigianVaolamChieu":"14:55:44","tThoigianNghiChieu":"15:03:53","tThoigianVaolamToi":null,"tThoigianNghiToi":null,"dNgayChamcong":"10-11-2020"},{"fK_iNhanvienID":3,"tThoigianVaolamSang":"07:57:56","tThoigianNghiSang":"12:03:51","tThoigianVaolamChieu":"13:13:37","tThoigianNghiChieu":"15:10:12","tThoigianVaolamToi":null,"tThoigianNghiToi":null,"dNgayChamcong":"10-11-2020"},{"fK_iNhanvienID":4,"tThoigianVaolamSang":"08:51:38","tThoigianNghiSang":"12:06:10","tThoigianVaolamChieu":"13:02:44","tThoigianNghiChieu":"15:02:02","tThoigianVaolamToi":null,"tThoigianNghiToi":null,"dNgayChamcong":"10-11-2020"},{"fK_iNhanvienID":5,"tThoigianVaolamSang":"07:11:47","tThoigianNghiSang":"12:09:34","tThoigianVaolamChieu":"13:01:04","tThoigianNghiChieu":"15:03:50","tThoigianVaolamToi":null,"tThoigianNghiToi":null,"dNgayChamcong":"10-11-2020"},{"fK_iNhanvienID":6,"tThoigianVaolamSang":"07:30:19","tThoigianNghiSang":"12:01:44","tThoigianVaolamChieu":"13:54:04","tThoigianNghiChieu":"15:04:19","tThoigianVaolamToi":null,"tThoigianNghiToi":null,"dNgayChamcong":"10-11-2020"},{"fK_iNhanvienID":7,"tThoigianVaolamSang":"07:08:14","tThoigianNghiSang":"12:02:01","tThoigianVaolamChieu":"13:46:14","tThoigianNghiChieu":"15:09:32","tThoigianVaolamToi":null,"tThoigianNghiToi":null,"dNgayChamcong":"10-11-2020"},{"fK_iNhanvienID":8,"tThoigianVaolamSang":"07:00:29","tThoigianNghiSang":"12:06:06","tThoigianVaolamChieu":"13:25:47","tThoigianNghiChieu":"15:01:13","tThoigianVaolamToi":null,"tThoigianNghiToi":null,"dNgayChamcong":"10-11-2020"},{"fK_iNhanvienID":9,"tThoigianVaolamSang":"07:28:29","tThoigianNghiSang":"12:06:20","tThoigianVaolamChieu":"13:46:08","tThoigianNghiChieu":"15:01:08","tThoigianVaolamToi":null,"tThoigianNghiToi":null,"dNgayChamcong":"10-11-2020"},{"fK_iNhanvienID":10,"tThoigianVaolamSang":"07:13:15","tThoigianNghiSang":"12:09:26","tThoigianVaolamChieu":"13:18:30","tThoigianNghiChieu":"15:03:18","tThoigianVaolamToi":null,"tThoigianNghiToi":null,"dNgayChamcong":"10-11-2020"},{"fK_iNhanvienID":11,"tThoigianVaolamSang":"07:39:28","tThoigianNghiSang":"12:02:29","tThoigianVaolamChieu":"13:19:12","tThoigianNghiChieu":"15:08:48","tThoigianVaolamToi":null,"tThoigianNghiToi":null,"dNgayChamcong":"10-11-2020"},{"fK_iNhanvienID":12,"tThoigianVaolamSang":"07:22:54","tThoigianNghiSang":"12:00:54","tThoigianVaolamChieu":"13:00:34","tThoigianNghiChieu":"15:06:33","tThoigianVaolamToi":null,"tThoigianNghiToi":null,"dNgayChamcong":"10-11-2020"},{"fK_iNhanvienID":13,"tThoigianVaolamSang":"07:50:54","tThoigianNghiSang":"12:00:28","tThoigianVaolamChieu":"13:59:41","tThoigianNghiChieu":"15:01:46","tThoigianVaolamToi":null,"tThoigianNghiToi":null,"dNgayChamcong":"10-11-2020"},{"fK_iNhanvienID":14,"tThoigianVaolamSang":"07:10:34","tThoigianNghiSang":"12:10:26","tThoigianVaolamChieu":"13:30:49","tThoigianNghiChieu":"15:02:28","tThoigianVaolamToi":null,"tThoigianNghiToi":null,"dNgayChamcong":"10-11-2020"},{"fK_iNhanvienID":15,"tThoigianVaolamSang":"07:11:33","tThoigianNghiSang":"12:09:20","tThoigianVaolamChieu":"13:57:16","tThoigianNghiChieu":"15:07:01","tThoigianVaolamToi":null,"tThoigianNghiToi":null,"dNgayChamcong":"10-11-2020"},{"fK_iNhanvienID":16,"tThoigianVaolamSang":"07:14:30","tThoigianNghiSang":"12:10:34","tThoigianVaolamChieu":"13:52:29","tThoigianNghiChieu":"15:02:27","tThoigianVaolamToi":null,"tThoigianNghiToi":null,"dNgayChamcong":"10-11-2020"},{"fK_iNhanvienID":17,"tThoigianVaolamSang":"07:02:28","tThoigianNghiSang":"12:09:03","tThoigianVaolamChieu":"13:59:16","tThoigianNghiChieu":"15:09:27","tThoigianVaolamToi":null,"tThoigianNghiToi":null,"dNgayChamcong":"10-11-2020"},{"fK_iNhanvienID":18,"tThoigianVaolamSang":"07:45:31","tThoigianNghiSang":"12:03:53","tThoigianVaolamChieu":"13:50:18","tThoigianNghiChieu":"15:04:56","tThoigianVaolamToi":null,"tThoigianNghiToi":null,"dNgayChamcong":"10-11-2020"},{"fK_iNhanvienID":19,"tThoigianVaolamSang":"07:38:11","tThoigianNghiSang":"12:00:39","tThoigianVaolamChieu":"13:46:45","tThoigianNghiChieu":"15:01:31","tThoigianVaolamToi":null,"tThoigianNghiToi":null,"dNgayChamcong":"10-11-2020"},{"fK_iNhanvienID":20,"tThoigianVaolamSang":"07:17:08","tThoigianNghiSang":"12:09:44","tThoigianVaolamChieu":"13:23:59","tThoigianNghiChieu":"15:04:13","tThoigianVaolamToi":null,"tThoigianNghiToi":null,"dNgayChamcong":"10-11-2020"},{"fK_iNhanvienID":21,"tThoigianVaolamSang":"07:23:46","tThoigianNghiSang":"12:03:21","tThoigianVaolamChieu":"13:24:47","tThoigianNghiChieu":"15:10:25","tThoigianVaolamToi":null,"tThoigianNghiToi":null,"dNgayChamcong":"10-11-2020"}]