[{"fK_iNhanvienID":"604e50f39c8b96835ba9ff97","tThoigianVaolamSang":"07:57:23","tThoigianNghiSang":"12:00:29","tThoigianVaolamChieu":"13:21:06","tThoigianNghiChieu":"17:30:39","tThoigianVaolamToi":null,"tThoigianNghiToi":null,"dNgayChamcong":"24-11-2021"},{"fK_iNhanvienID":"605ea67db4c6befeb4b73e9d","tThoigianVaolamSang":"07:37:14","tThoigianNghiSang":"12:02:15","tThoigianVaolamChieu":"13:19:16","tThoigianNghiChieu":"17:35:37","tThoigianVaolamToi":null,"tThoigianNghiToi":null,"dNgayChamcong":"24-11-2021"},{"fK_iNhanvienID":"605ed0c04f8b3c1689f19b88","tThoigianVaolamSang":"07:56:22","tThoigianNghiSang":"12:05:04","tThoigianVaolamChieu":"14:26:22","tThoigianNghiChieu":"17:31:26","tThoigianVaolamToi":null,"tThoigianNghiToi":null,"dNgayChamcong":"24-11-2021"},{"fK_iNhanvienID":"605ed1094f8b3c1689f19b8a","tThoigianVaolamSang":"07:30:47","tThoigianNghiSang":"12:06:14","tThoigianVaolamChieu":"13:03:14","tThoigianNghiChieu":"17:32:13","tThoigianVaolamToi":null,"tThoigianNghiToi":null,"dNgayChamcong":"24-11-2021"},{"fK_iNhanvienID":"605ed1774f8b3c1689f19b8c","tThoigianVaolamSang":"07:45:57","tThoigianNghiSang":"12:05:18","tThoigianVaolamChieu":"13:45:02","tThoigianNghiChieu":"17:39:27","tThoigianVaolamToi":null,"tThoigianNghiToi":null,"dNgayChamcong":"24-11-2021"},{"fK_iNhanvienID":"605ed3534f8b3c1689f19b8e","tThoigianVaolamSang":"08:10:15","tThoigianNghiSang":"12:05:09","tThoigianVaolamChieu":"14:30:03","tThoigianNghiChieu":"17:37:21","tThoigianVaolamToi":null,"tThoigianNghiToi":null,"dNgayChamcong":"24-11-2021"},{"fK_iNhanvienID":"605ed4ba4f8b3c1689f19b90","tThoigianVaolamSang":"07:41:52","tThoigianNghiSang":"12:09:20","tThoigianVaolamChieu":"13:43:57","tThoigianNghiChieu":"17:40:22","tThoigianVaolamToi":null,"tThoigianNghiToi":null,"dNgayChamcong":"24-11-2021"},{"fK_iNhanvienID":"605ed6144f8b3c1689f19b92","tThoigianVaolamSang":"08:10:37","tThoigianNghiSang":"12:08:23","tThoigianVaolamChieu":"13:00:22","tThoigianNghiChieu":"17:30:30","tThoigianVaolamToi":null,"tThoigianNghiToi":null,"dNgayChamcong":"24-11-2021"},{"fK_iNhanvienID":"605ed6684f8b3c1689f19b94","tThoigianVaolamSang":"07:54:31","tThoigianNghiSang":"12:08:00","tThoigianVaolamChieu":"13:09:43","tThoigianNghiChieu":"17:40:25","tThoigianVaolamToi":null,"tThoigianNghiToi":null,"dNgayChamcong":"24-11-2021"},{"fK_iNhanvienID":"605ed6ad4f8b3c1689f19b96","tThoigianVaolamSang":"08:02:00","tThoigianNghiSang":"12:01:27","tThoigianVaolamChieu":"13:58:01","tThoigianNghiChieu":"17:38:46","tThoigianVaolamToi":null,"tThoigianNghiToi":null,"dNgayChamcong":"24-11-2021"},{"fK_iNhanvienID":"605ed7504f8b3c1689f19b98","tThoigianVaolamSang":"07:33:22","tThoigianNghiSang":"12:08:34","tThoigianVaolamChieu":"13:27:42","tThoigianNghiChieu":"17:39:08","tThoigianVaolamToi":null,"tThoigianNghiToi":null,"dNgayChamcong":"24-11-2021"},{"fK_iNhanvienID":"605ed80f4f8b3c1689f19b9a","tThoigianVaolamSang":"08:01:12","tThoigianNghiSang":"12:02:00","tThoigianVaolamChieu":"13:30:09","tThoigianNghiChieu":"17:40:28","tThoigianVaolamToi":null,"tThoigianNghiToi":null,"dNgayChamcong":"24-11-2021"},{"fK_iNhanvienID":"605ed9484f8b3c1689f19b9d","tThoigianVaolamSang":"07:39:33","tThoigianNghiSang":"12:06:25","tThoigianVaolamChieu":"13:19:55","tThoigianNghiChieu":"17:33:34","tThoigianVaolamToi":null,"tThoigianNghiToi":null,"dNgayChamcong":"24-11-2021"},{"fK_iNhanvienID":"605ed9884f8b3c1689f19b9f","tThoigianVaolamSang":"07:48:00","tThoigianNghiSang":"12:04:39","tThoigianVaolamChieu":"13:14:28","tThoigianNghiChieu":"17:38:31","tThoigianVaolamToi":null,"tThoigianNghiToi":null,"dNgayChamcong":"24-11-2021"},{"fK_iNhanvienID":"605eda0e4f8b3c1689f19ba1","tThoigianVaolamSang":"07:57:56","tThoigianNghiSang":"12:07:33","tThoigianVaolamChieu":"13:32:30","tThoigianNghiChieu":"17:34:22","tThoigianVaolamToi":null,"tThoigianNghiToi":null,"dNgayChamcong":"24-11-2021"},{"fK_iNhanvienID":"605eda814f8b3c1689f19ba3","tThoigianVaolamSang":"07:48:26","tThoigianNghiSang":"12:09:43","tThoigianVaolamChieu":"13:51:38","tThoigianNghiChieu":"17:40:22","tThoigianVaolamToi":null,"tThoigianNghiToi":null,"dNgayChamcong":"24-11-2021"},{"fK_iNhanvienID":"605edb09bd0d3a60ae2846ba","tThoigianVaolamSang":"08:07:03","tThoigianNghiSang":"12:03:28","tThoigianVaolamChieu":"13:07:55","tThoigianNghiChieu":"17:36:51","tThoigianVaolamToi":null,"tThoigianNghiToi":null,"dNgayChamcong":"24-11-2021"},{"fK_iNhanvienID":"605edb4cbd0d3a60ae2846bc","tThoigianVaolamSang":"07:37:39","tThoigianNghiSang":"12:05:02","tThoigianVaolamChieu":"13:45:56","tThoigianNghiChieu":"17:30:35","tThoigianVaolamToi":null,"tThoigianNghiToi":null,"dNgayChamcong":"24-11-2021"},{"fK_iNhanvienID":"605edb94bd0d3a60ae2846be","tThoigianVaolamSang":"07:30:08","tThoigianNghiSang":"12:05:32","tThoigianVaolamChieu":"13:53:11","tThoigianNghiChieu":"17:39:07","tThoigianVaolamToi":null,"tThoigianNghiToi":null,"dNgayChamcong":"24-11-2021"},{"fK_iNhanvienID":"605edbd1bd0d3a60ae2846c0","tThoigianVaolamSang":"07:37:02","tThoigianNghiSang":"12:04:12","tThoigianVaolamChieu":"13:33:14","tThoigianNghiChieu":"17:30:16","tThoigianVaolamToi":null,"tThoigianNghiToi":null,"dNgayChamcong":"24-11-2021"}]