[{"fK_iNhanvienID":1,"tThoigianVaolamSang":"08:45:08","tThoigianNghiSang":"12:06:32","tThoigianVaolamChieu":"14:08:40","tThoigianNghiChieu":"15:03:18","tThoigianVaolamToi":null,"tThoigianNghiToi":null,"dNgayChamcong":"14-08-2019"},{"fK_iNhanvienID":2,"tThoigianVaolamSang":"07:02:04","tThoigianNghiSang":"12:10:52","tThoigianVaolamChieu":"13:39:37","tThoigianNghiChieu":"15:01:24","tThoigianVaolamToi":null,"tThoigianNghiToi":null,"dNgayChamcong":"14-08-2019"},{"fK_iNhanvienID":3,"tThoigianVaolamSang":"07:48:15","tThoigianNghiSang":"12:02:41","tThoigianVaolamChieu":"13:50:01","tThoigianNghiChieu":"15:06:33","tThoigianVaolamToi":null,"tThoigianNghiToi":null,"dNgayChamcong":"14-08-2019"},{"fK_iNhanvienID":4,"tThoigianVaolamSang":"08:18:39","tThoigianNghiSang":"12:04:12","tThoigianVaolamChieu":"13:22:44","tThoigianNghiChieu":"15:10:34","tThoigianVaolamToi":null,"tThoigianNghiToi":null,"dNgayChamcong":"14-08-2019"},{"fK_iNhanvienID":5,"tThoigianVaolamSang":"08:44:54","tThoigianNghiSang":"12:01:54","tThoigianVaolamChieu":"14:40:27","tThoigianNghiChieu":"15:08:50","tThoigianVaolamToi":null,"tThoigianNghiToi":null,"dNgayChamcong":"14-08-2019"},{"fK_iNhanvienID":6,"tThoigianVaolamSang":"07:44:05","tThoigianNghiSang":"12:10:54","tThoigianVaolamChieu":"13:04:05","tThoigianNghiChieu":"15:01:37","tThoigianVaolamToi":null,"tThoigianNghiToi":null,"dNgayChamcong":"14-08-2019"},{"fK_iNhanvienID":7,"tThoigianVaolamSang":"07:28:21","tThoigianNghiSang":"12:09:55","tThoigianVaolamChieu":"13:59:12","tThoigianNghiChieu":"15:00:52","tThoigianVaolamToi":null,"tThoigianNghiToi":null,"dNgayChamcong":"14-08-2019"},{"fK_iNhanvienID":8,"tThoigianVaolamSang":"08:22:02","tThoigianNghiSang":"12:03:00","tThoigianVaolamChieu":"13:33:59","tThoigianNghiChieu":"15:10:13","tThoigianVaolamToi":null,"tThoigianNghiToi":null,"dNgayChamcong":"14-08-2019"},{"fK_iNhanvienID":9,"tThoigianVaolamSang":"08:47:26","tThoigianNghiSang":"12:00:35","tThoigianVaolamChieu":"13:52:00","tThoigianNghiChieu":"15:01:11","tThoigianVaolamToi":null,"tThoigianNghiToi":null,"dNgayChamcong":"14-08-2019"},{"fK_iNhanvienID":10,"tThoigianVaolamSang":"07:05:20","tThoigianNghiSang":"12:06:42","tThoigianVaolamChieu":"13:05:37","tThoigianNghiChieu":"15:10:44","tThoigianVaolamToi":null,"tThoigianNghiToi":null,"dNgayChamcong":"14-08-2019"},{"fK_iNhanvienID":11,"tThoigianVaolamSang":"08:23:16","tThoigianNghiSang":"12:08:30","tThoigianVaolamChieu":"13:01:18","tThoigianNghiChieu":"15:08:17","tThoigianVaolamToi":null,"tThoigianNghiToi":null,"dNgayChamcong":"14-08-2019"},{"fK_iNhanvienID":12,"tThoigianVaolamSang":"08:18:36","tThoigianNghiSang":"12:06:18","tThoigianVaolamChieu":"13:09:13","tThoigianNghiChieu":"15:07:02","tThoigianVaolamToi":null,"tThoigianNghiToi":null,"dNgayChamcong":"14-08-2019"},{"fK_iNhanvienID":13,"tThoigianVaolamSang":"08:47:45","tThoigianNghiSang":"12:02:50","tThoigianVaolamChieu":"13:48:15","tThoigianNghiChieu":"15:08:28","tThoigianVaolamToi":null,"tThoigianNghiToi":null,"dNgayChamcong":"14-08-2019"},{"fK_iNhanvienID":14,"tThoigianVaolamSang":"07:53:11","tThoigianNghiSang":"12:00:08","tThoigianVaolamChieu":"13:05:53","tThoigianNghiChieu":"15:09:24","tThoigianVaolamToi":null,"tThoigianNghiToi":null,"dNgayChamcong":"14-08-2019"},{"fK_iNhanvienID":15,"tThoigianVaolamSang":"08:40:07","tThoigianNghiSang":"12:03:58","tThoigianVaolamChieu":"13:14:07","tThoigianNghiChieu":"15:05:14","tThoigianVaolamToi":null,"tThoigianNghiToi":null,"dNgayChamcong":"14-08-2019"},{"fK_iNhanvienID":16,"tThoigianVaolamSang":"07:09:28","tThoigianNghiSang":"12:03:25","tThoigianVaolamChieu":"13:24:42","tThoigianNghiChieu":"15:02:20","tThoigianVaolamToi":null,"tThoigianNghiToi":null,"dNgayChamcong":"14-08-2019"},{"fK_iNhanvienID":17,"tThoigianVaolamSang":"07:51:26","tThoigianNghiSang":"12:02:56","tThoigianVaolamChieu":"13:36:37","tThoigianNghiChieu":"15:01:46","tThoigianVaolamToi":null,"tThoigianNghiToi":null,"dNgayChamcong":"14-08-2019"},{"fK_iNhanvienID":18,"tThoigianVaolamSang":"07:26:01","tThoigianNghiSang":"12:00:09","tThoigianVaolamChieu":"13:17:08","tThoigianNghiChieu":"15:00:43","tThoigianVaolamToi":null,"tThoigianNghiToi":null,"dNgayChamcong":"14-08-2019"},{"fK_iNhanvienID":19,"tThoigianVaolamSang":"07:26:54","tThoigianNghiSang":"12:00:35","tThoigianVaolamChieu":"13:40:22","tThoigianNghiChieu":"15:08:52","tThoigianVaolamToi":null,"tThoigianNghiToi":null,"dNgayChamcong":"14-08-2019"},{"fK_iNhanvienID":20,"tThoigianVaolamSang":"07:58:49","tThoigianNghiSang":"12:01:49","tThoigianVaolamChieu":"13:36:04","tThoigianNghiChieu":"15:07:50","tThoigianVaolamToi":null,"tThoigianNghiToi":null,"dNgayChamcong":"14-08-2019"},{"fK_iNhanvienID":21,"tThoigianVaolamSang":"07:51:02","tThoigianNghiSang":"12:09:51","tThoigianVaolamChieu":"13:39:52","tThoigianNghiChieu":"15:00:11","tThoigianVaolamToi":null,"tThoigianNghiToi":null,"dNgayChamcong":"14-08-2019"}]