[{"fK_iNhanvienID":1,"tThoigianVaolamSang":"08:00:10","tThoigianNghiSang":"12:06:49","tThoigianVaolamChieu":"13:36:29","tThoigianNghiChieu":"15:08:49","tThoigianVaolamToi":null,"tThoigianNghiToi":null,"dNgayChamcong":"10-04-2019"},{"fK_iNhanvienID":2,"tThoigianVaolamSang":"08:11:32","tThoigianNghiSang":"12:10:06","tThoigianVaolamChieu":"13:14:24","tThoigianNghiChieu":"15:03:31","tThoigianVaolamToi":null,"tThoigianNghiToi":null,"dNgayChamcong":"10-04-2019"},{"fK_iNhanvienID":3,"tThoigianVaolamSang":"07:30:28","tThoigianNghiSang":"12:03:42","tThoigianVaolamChieu":"13:00:27","tThoigianNghiChieu":"15:05:39","tThoigianVaolamToi":null,"tThoigianNghiToi":null,"dNgayChamcong":"10-04-2019"},{"fK_iNhanvienID":4,"tThoigianVaolamSang":"07:24:10","tThoigianNghiSang":"12:01:22","tThoigianVaolamChieu":"13:12:33","tThoigianNghiChieu":"15:05:07","tThoigianVaolamToi":null,"tThoigianNghiToi":null,"dNgayChamcong":"10-04-2019"},{"fK_iNhanvienID":5,"tThoigianVaolamSang":"07:00:55","tThoigianNghiSang":"12:09:32","tThoigianVaolamChieu":"13:23:43","tThoigianNghiChieu":"15:02:46","tThoigianVaolamToi":null,"tThoigianNghiToi":null,"dNgayChamcong":"10-04-2019"},{"fK_iNhanvienID":6,"tThoigianVaolamSang":"07:31:10","tThoigianNghiSang":"12:02:48","tThoigianVaolamChieu":"13:21:21","tThoigianNghiChieu":"15:07:57","tThoigianVaolamToi":null,"tThoigianNghiToi":null,"dNgayChamcong":"10-04-2019"},{"fK_iNhanvienID":7,"tThoigianVaolamSang":"07:48:43","tThoigianNghiSang":"12:08:05","tThoigianVaolamChieu":"13:20:39","tThoigianNghiChieu":"15:09:08","tThoigianVaolamToi":null,"tThoigianNghiToi":null,"dNgayChamcong":"10-04-2019"},{"fK_iNhanvienID":8,"tThoigianVaolamSang":"07:01:32","tThoigianNghiSang":"12:01:44","tThoigianVaolamChieu":"13:51:25","tThoigianNghiChieu":"15:06:07","tThoigianVaolamToi":null,"tThoigianNghiToi":null,"dNgayChamcong":"10-04-2019"},{"fK_iNhanvienID":9,"tThoigianVaolamSang":"08:44:40","tThoigianNghiSang":"12:07:30","tThoigianVaolamChieu":"13:05:14","tThoigianNghiChieu":"15:00:38","tThoigianVaolamToi":null,"tThoigianNghiToi":null,"dNgayChamcong":"10-04-2019"},{"fK_iNhanvienID":10,"tThoigianVaolamSang":"08:56:43","tThoigianNghiSang":"12:09:10","tThoigianVaolamChieu":"13:52:35","tThoigianNghiChieu":"15:07:26","tThoigianVaolamToi":null,"tThoigianNghiToi":null,"dNgayChamcong":"10-04-2019"},{"fK_iNhanvienID":11,"tThoigianVaolamSang":"07:23:50","tThoigianNghiSang":"12:06:41","tThoigianVaolamChieu":"13:39:53","tThoigianNghiChieu":"15:01:02","tThoigianVaolamToi":null,"tThoigianNghiToi":null,"dNgayChamcong":"10-04-2019"},{"fK_iNhanvienID":12,"tThoigianVaolamSang":"07:06:24","tThoigianNghiSang":"12:07:53","tThoigianVaolamChieu":"13:43:59","tThoigianNghiChieu":"15:03:42","tThoigianVaolamToi":null,"tThoigianNghiToi":null,"dNgayChamcong":"10-04-2019"},{"fK_iNhanvienID":13,"tThoigianVaolamSang":"07:32:14","tThoigianNghiSang":"12:03:18","tThoigianVaolamChieu":"13:49:21","tThoigianNghiChieu":"15:04:34","tThoigianVaolamToi":null,"tThoigianNghiToi":null,"dNgayChamcong":"10-04-2019"},{"fK_iNhanvienID":14,"tThoigianVaolamSang":"07:10:43","tThoigianNghiSang":"12:01:45","tThoigianVaolamChieu":"13:19:23","tThoigianNghiChieu":"15:05:04","tThoigianVaolamToi":null,"tThoigianNghiToi":null,"dNgayChamcong":"10-04-2019"},{"fK_iNhanvienID":15,"tThoigianVaolamSang":"07:41:41","tThoigianNghiSang":"12:07:49","tThoigianVaolamChieu":"13:40:54","tThoigianNghiChieu":"15:04:29","tThoigianVaolamToi":null,"tThoigianNghiToi":null,"dNgayChamcong":"10-04-2019"},{"fK_iNhanvienID":16,"tThoigianVaolamSang":"07:54:58","tThoigianNghiSang":"12:06:09","tThoigianVaolamChieu":"13:15:55","tThoigianNghiChieu":"15:03:08","tThoigianVaolamToi":null,"tThoigianNghiToi":null,"dNgayChamcong":"10-04-2019"},{"fK_iNhanvienID":17,"tThoigianVaolamSang":"07:07:02","tThoigianNghiSang":"12:05:34","tThoigianVaolamChieu":"13:00:24","tThoigianNghiChieu":"15:02:31","tThoigianVaolamToi":null,"tThoigianNghiToi":null,"dNgayChamcong":"10-04-2019"},{"fK_iNhanvienID":18,"tThoigianVaolamSang":"07:37:25","tThoigianNghiSang":"12:10:45","tThoigianVaolamChieu":"13:40:00","tThoigianNghiChieu":"15:09:39","tThoigianVaolamToi":null,"tThoigianNghiToi":null,"dNgayChamcong":"10-04-2019"},{"fK_iNhanvienID":19,"tThoigianVaolamSang":"07:25:34","tThoigianNghiSang":"12:03:00","tThoigianVaolamChieu":"13:56:57","tThoigianNghiChieu":"15:04:39","tThoigianVaolamToi":null,"tThoigianNghiToi":null,"dNgayChamcong":"10-04-2019"},{"fK_iNhanvienID":20,"tThoigianVaolamSang":"07:22:40","tThoigianNghiSang":"12:09:20","tThoigianVaolamChieu":"13:56:11","tThoigianNghiChieu":"15:07:04","tThoigianVaolamToi":null,"tThoigianNghiToi":null,"dNgayChamcong":"10-04-2019"},{"fK_iNhanvienID":21,"tThoigianVaolamSang":"07:30:38","tThoigianNghiSang":"12:07:28","tThoigianVaolamChieu":"13:07:03","tThoigianNghiChieu":"15:07:41","tThoigianVaolamToi":null,"tThoigianNghiToi":null,"dNgayChamcong":"10-04-2019"}]