[{"fK_iNhanvienID":"604e50f39c8b96835ba9ff97","tThoigianVaolamSang":"07:24:28","tThoigianNghiSang":"12:04:10","tThoigianVaolamChieu":"13:37:44","tThoigianNghiChieu":"15:09:53","tThoigianVaolamToi":null,"tThoigianNghiToi":null,"dNgayChamcong":"06-05-2019"},{"fK_iNhanvienID":"60555964d242573c7742cf34","tThoigianVaolamSang":"08:06:51","tThoigianNghiSang":"12:04:01","tThoigianVaolamChieu":"13:20:00","tThoigianNghiChieu":"15:03:58","tThoigianVaolamToi":null,"tThoigianNghiToi":null,"dNgayChamcong":"06-05-2019"},{"fK_iNhanvienID":"605569230fe553fa0f49c29e","tThoigianVaolamSang":"07:57:57","tThoigianNghiSang":"12:05:47","tThoigianVaolamChieu":"13:53:11","tThoigianNghiChieu":"15:00:26","tThoigianVaolamToi":null,"tThoigianNghiToi":null,"dNgayChamcong":"06-05-2019"}]