[{"fK_iNhanvienID":"604e50f39c8b96835ba9ff97","tThoigianVaolamSang":"07:41:02","tThoigianNghiSang":"12:07:49","tThoigianVaolamChieu":"14:02:58","tThoigianNghiChieu":"17:37:33","tThoigianVaolamToi":null,"tThoigianNghiToi":null,"dNgayChamcong":"22-06-2020"},{"fK_iNhanvienID":"605ea67db4c6befeb4b73e9d","tThoigianVaolamSang":"08:11:18","tThoigianNghiSang":"12:04:49","tThoigianVaolamChieu":"14:48:39","tThoigianNghiChieu":"17:33:47","tThoigianVaolamToi":null,"tThoigianNghiToi":null,"dNgayChamcong":"22-06-2020"},{"fK_iNhanvienID":"605ed0c04f8b3c1689f19b88","tThoigianVaolamSang":"08:05:21","tThoigianNghiSang":"12:03:58","tThoigianVaolamChieu":"13:39:03","tThoigianNghiChieu":"17:35:46","tThoigianVaolamToi":null,"tThoigianNghiToi":null,"dNgayChamcong":"22-06-2020"},{"fK_iNhanvienID":"605ed1094f8b3c1689f19b8a","tThoigianVaolamSang":"07:36:29","tThoigianNghiSang":"12:02:38","tThoigianVaolamChieu":"13:45:16","tThoigianNghiChieu":"17:37:39","tThoigianVaolamToi":null,"tThoigianNghiToi":null,"dNgayChamcong":"22-06-2020"},{"fK_iNhanvienID":"605ed1774f8b3c1689f19b8c","tThoigianVaolamSang":"07:56:30","tThoigianNghiSang":"12:08:11","tThoigianVaolamChieu":"13:28:37","tThoigianNghiChieu":"17:35:38","tThoigianVaolamToi":null,"tThoigianNghiToi":null,"dNgayChamcong":"22-06-2020"},{"fK_iNhanvienID":"605ed3534f8b3c1689f19b8e","tThoigianVaolamSang":"07:59:28","tThoigianNghiSang":"12:08:49","tThoigianVaolamChieu":"13:21:14","tThoigianNghiChieu":"17:35:48","tThoigianVaolamToi":null,"tThoigianNghiToi":null,"dNgayChamcong":"22-06-2020"},{"fK_iNhanvienID":"605ed4ba4f8b3c1689f19b90","tThoigianVaolamSang":"07:32:50","tThoigianNghiSang":"12:05:51","tThoigianVaolamChieu":"13:36:02","tThoigianNghiChieu":"17:32:52","tThoigianVaolamToi":null,"tThoigianNghiToi":null,"dNgayChamcong":"22-06-2020"},{"fK_iNhanvienID":"605ed6144f8b3c1689f19b92","tThoigianVaolamSang":"07:35:19","tThoigianNghiSang":"12:09:39","tThoigianVaolamChieu":"13:17:41","tThoigianNghiChieu":"17:37:31","tThoigianVaolamToi":null,"tThoigianNghiToi":null,"dNgayChamcong":"22-06-2020"},{"fK_iNhanvienID":"605ed6684f8b3c1689f19b94","tThoigianVaolamSang":"07:47:23","tThoigianNghiSang":"12:05:44","tThoigianVaolamChieu":"13:31:48","tThoigianNghiChieu":"17:32:20","tThoigianVaolamToi":null,"tThoigianNghiToi":null,"dNgayChamcong":"22-06-2020"},{"fK_iNhanvienID":"605ed6ad4f8b3c1689f19b96","tThoigianVaolamSang":"07:59:29","tThoigianNghiSang":"12:06:48","tThoigianVaolamChieu":"13:03:06","tThoigianNghiChieu":"17:30:01","tThoigianVaolamToi":null,"tThoigianNghiToi":null,"dNgayChamcong":"22-06-2020"},{"fK_iNhanvienID":"605ed7504f8b3c1689f19b98","tThoigianVaolamSang":"07:30:35","tThoigianNghiSang":"12:07:38","tThoigianVaolamChieu":"13:22:50","tThoigianNghiChieu":"17:36:14","tThoigianVaolamToi":null,"tThoigianNghiToi":null,"dNgayChamcong":"22-06-2020"},{"fK_iNhanvienID":"605ed80f4f8b3c1689f19b9a","tThoigianVaolamSang":"07:44:54","tThoigianNghiSang":"12:05:49","tThoigianVaolamChieu":"13:59:18","tThoigianNghiChieu":"17:34:03","tThoigianVaolamToi":null,"tThoigianNghiToi":null,"dNgayChamcong":"22-06-2020"},{"fK_iNhanvienID":"605ed9484f8b3c1689f19b9d","tThoigianVaolamSang":"07:32:38","tThoigianNghiSang":"12:10:17","tThoigianVaolamChieu":"13:47:07","tThoigianNghiChieu":"17:30:55","tThoigianVaolamToi":null,"tThoigianNghiToi":null,"dNgayChamcong":"22-06-2020"},{"fK_iNhanvienID":"605ed9884f8b3c1689f19b9f","tThoigianVaolamSang":"07:38:22","tThoigianNghiSang":"12:02:24","tThoigianVaolamChieu":"13:06:07","tThoigianNghiChieu":"17:39:15","tThoigianVaolamToi":null,"tThoigianNghiToi":null,"dNgayChamcong":"22-06-2020"},{"fK_iNhanvienID":"605eda0e4f8b3c1689f19ba1","tThoigianVaolamSang":"07:46:13","tThoigianNghiSang":"12:06:11","tThoigianVaolamChieu":"13:45:32","tThoigianNghiChieu":"17:37:50","tThoigianVaolamToi":null,"tThoigianNghiToi":null,"dNgayChamcong":"22-06-2020"},{"fK_iNhanvienID":"605eda814f8b3c1689f19ba3","tThoigianVaolamSang":"07:30:21","tThoigianNghiSang":"12:05:13","tThoigianVaolamChieu":"13:58:31","tThoigianNghiChieu":"17:37:22","tThoigianVaolamToi":null,"tThoigianNghiToi":null,"dNgayChamcong":"22-06-2020"},{"fK_iNhanvienID":"605edb09bd0d3a60ae2846ba","tThoigianVaolamSang":"07:44:16","tThoigianNghiSang":"12:08:24","tThoigianVaolamChieu":"13:01:30","tThoigianNghiChieu":"17:35:23","tThoigianVaolamToi":null,"tThoigianNghiToi":null,"dNgayChamcong":"22-06-2020"},{"fK_iNhanvienID":"605edb4cbd0d3a60ae2846bc","tThoigianVaolamSang":"07:58:40","tThoigianNghiSang":"12:01:46","tThoigianVaolamChieu":"13:20:54","tThoigianNghiChieu":"17:36:37","tThoigianVaolamToi":null,"tThoigianNghiToi":null,"dNgayChamcong":"22-06-2020"},{"fK_iNhanvienID":"605edb94bd0d3a60ae2846be","tThoigianVaolamSang":"07:54:31","tThoigianNghiSang":"12:05:21","tThoigianVaolamChieu":"13:52:26","tThoigianNghiChieu":"17:35:26","tThoigianVaolamToi":null,"tThoigianNghiToi":null,"dNgayChamcong":"22-06-2020"},{"fK_iNhanvienID":"605edbd1bd0d3a60ae2846c0","tThoigianVaolamSang":"07:45:29","tThoigianNghiSang":"12:01:39","tThoigianVaolamChieu":"13:05:25","tThoigianNghiChieu":"17:32:57","tThoigianVaolamToi":null,"tThoigianNghiToi":null,"dNgayChamcong":"22-06-2020"}]