[{"fK_iNhanvienID":1,"tThoigianVaolamSang":"07:25:48","tThoigianNghiSang":"12:10:54","tThoigianVaolamChieu":"13:22:41","tThoigianNghiChieu":"15:06:06","tThoigianVaolamToi":null,"tThoigianNghiToi":null,"dNgayChamcong":"16-04-2019"},{"fK_iNhanvienID":2,"tThoigianVaolamSang":"07:30:21","tThoigianNghiSang":"12:01:26","tThoigianVaolamChieu":"13:25:30","tThoigianNghiChieu":"15:05:51","tThoigianVaolamToi":null,"tThoigianNghiToi":null,"dNgayChamcong":"16-04-2019"},{"fK_iNhanvienID":3,"tThoigianVaolamSang":"07:35:10","tThoigianNghiSang":"12:02:16","tThoigianVaolamChieu":"13:01:18","tThoigianNghiChieu":"15:06:14","tThoigianVaolamToi":null,"tThoigianNghiToi":null,"dNgayChamcong":"16-04-2019"},{"fK_iNhanvienID":4,"tThoigianVaolamSang":"08:10:06","tThoigianNghiSang":"12:05:10","tThoigianVaolamChieu":"14:59:12","tThoigianNghiChieu":"15:06:51","tThoigianVaolamToi":null,"tThoigianNghiToi":null,"dNgayChamcong":"16-04-2019"},{"fK_iNhanvienID":5,"tThoigianVaolamSang":"07:57:02","tThoigianNghiSang":"12:06:26","tThoigianVaolamChieu":"13:42:03","tThoigianNghiChieu":"15:07:32","tThoigianVaolamToi":null,"tThoigianNghiToi":null,"dNgayChamcong":"16-04-2019"},{"fK_iNhanvienID":6,"tThoigianVaolamSang":"08:53:25","tThoigianNghiSang":"12:10:39","tThoigianVaolamChieu":"13:21:16","tThoigianNghiChieu":"15:01:48","tThoigianVaolamToi":null,"tThoigianNghiToi":null,"dNgayChamcong":"16-04-2019"},{"fK_iNhanvienID":7,"tThoigianVaolamSang":"08:44:11","tThoigianNghiSang":"12:03:34","tThoigianVaolamChieu":"13:30:58","tThoigianNghiChieu":"15:02:32","tThoigianVaolamToi":null,"tThoigianNghiToi":null,"dNgayChamcong":"16-04-2019"},{"fK_iNhanvienID":8,"tThoigianVaolamSang":"07:00:27","tThoigianNghiSang":"12:04:46","tThoigianVaolamChieu":"13:59:14","tThoigianNghiChieu":"15:02:00","tThoigianVaolamToi":null,"tThoigianNghiToi":null,"dNgayChamcong":"16-04-2019"},{"fK_iNhanvienID":9,"tThoigianVaolamSang":"07:53:59","tThoigianNghiSang":"12:05:52","tThoigianVaolamChieu":"13:40:52","tThoigianNghiChieu":"15:10:43","tThoigianVaolamToi":null,"tThoigianNghiToi":null,"dNgayChamcong":"16-04-2019"},{"fK_iNhanvienID":10,"tThoigianVaolamSang":"08:28:21","tThoigianNghiSang":"12:02:32","tThoigianVaolamChieu":"13:23:53","tThoigianNghiChieu":"15:10:13","tThoigianVaolamToi":null,"tThoigianNghiToi":null,"dNgayChamcong":"16-04-2019"},{"fK_iNhanvienID":11,"tThoigianVaolamSang":"08:49:57","tThoigianNghiSang":"12:09:43","tThoigianVaolamChieu":"13:31:43","tThoigianNghiChieu":"15:01:38","tThoigianVaolamToi":null,"tThoigianNghiToi":null,"dNgayChamcong":"16-04-2019"},{"fK_iNhanvienID":12,"tThoigianVaolamSang":"08:59:29","tThoigianNghiSang":"12:01:33","tThoigianVaolamChieu":"13:06:06","tThoigianNghiChieu":"15:10:10","tThoigianVaolamToi":null,"tThoigianNghiToi":null,"dNgayChamcong":"16-04-2019"},{"fK_iNhanvienID":13,"tThoigianVaolamSang":"07:08:17","tThoigianNghiSang":"12:06:31","tThoigianVaolamChieu":"13:53:26","tThoigianNghiChieu":"15:06:54","tThoigianVaolamToi":null,"tThoigianNghiToi":null,"dNgayChamcong":"16-04-2019"},{"fK_iNhanvienID":14,"tThoigianVaolamSang":"07:49:42","tThoigianNghiSang":"12:04:30","tThoigianVaolamChieu":"13:17:01","tThoigianNghiChieu":"15:07:36","tThoigianVaolamToi":null,"tThoigianNghiToi":null,"dNgayChamcong":"16-04-2019"},{"fK_iNhanvienID":15,"tThoigianVaolamSang":"07:55:33","tThoigianNghiSang":"12:08:39","tThoigianVaolamChieu":"13:31:56","tThoigianNghiChieu":"15:02:47","tThoigianVaolamToi":null,"tThoigianNghiToi":null,"dNgayChamcong":"16-04-2019"},{"fK_iNhanvienID":16,"tThoigianVaolamSang":"07:42:23","tThoigianNghiSang":"12:04:46","tThoigianVaolamChieu":"13:26:30","tThoigianNghiChieu":"15:04:46","tThoigianVaolamToi":null,"tThoigianNghiToi":null,"dNgayChamcong":"16-04-2019"},{"fK_iNhanvienID":17,"tThoigianVaolamSang":"07:09:11","tThoigianNghiSang":"12:05:16","tThoigianVaolamChieu":"13:14:39","tThoigianNghiChieu":"15:05:21","tThoigianVaolamToi":null,"tThoigianNghiToi":null,"dNgayChamcong":"16-04-2019"},{"fK_iNhanvienID":18,"tThoigianVaolamSang":"07:19:58","tThoigianNghiSang":"12:01:21","tThoigianVaolamChieu":"13:24:42","tThoigianNghiChieu":"15:07:59","tThoigianVaolamToi":null,"tThoigianNghiToi":null,"dNgayChamcong":"16-04-2019"},{"fK_iNhanvienID":19,"tThoigianVaolamSang":"07:54:24","tThoigianNghiSang":"12:10:44","tThoigianVaolamChieu":"13:09:27","tThoigianNghiChieu":"15:07:42","tThoigianVaolamToi":null,"tThoigianNghiToi":null,"dNgayChamcong":"16-04-2019"},{"fK_iNhanvienID":20,"tThoigianVaolamSang":"07:09:24","tThoigianNghiSang":"12:10:09","tThoigianVaolamChieu":"13:41:35","tThoigianNghiChieu":"15:10:41","tThoigianVaolamToi":null,"tThoigianNghiToi":null,"dNgayChamcong":"16-04-2019"},{"fK_iNhanvienID":21,"tThoigianVaolamSang":"07:35:17","tThoigianNghiSang":"12:08:16","tThoigianVaolamChieu":"13:24:32","tThoigianNghiChieu":"15:08:17","tThoigianVaolamToi":null,"tThoigianNghiToi":null,"dNgayChamcong":"16-04-2019"}]