[{"fK_iNhanvienID":"604e50f39c8b96835ba9ff97","tThoigianVaolamSang":"07:24:00","tThoigianNghiSang":"12:10:52","tThoigianVaolamChieu":"13:06:43","tThoigianNghiChieu":"15:10:19","tThoigianVaolamToi":null,"tThoigianNghiToi":null,"dNgayChamcong":"11-01-2021"},{"fK_iNhanvienID":"60555964d242573c7742cf34","tThoigianVaolamSang":"07:30:38","tThoigianNghiSang":"12:02:15","tThoigianVaolamChieu":"13:33:18","tThoigianNghiChieu":"15:08:10","tThoigianVaolamToi":null,"tThoigianNghiToi":null,"dNgayChamcong":"11-01-2021"},{"fK_iNhanvienID":"605569230fe553fa0f49c29e","tThoigianVaolamSang":"07:44:11","tThoigianNghiSang":"12:05:51","tThoigianVaolamChieu":"14:07:45","tThoigianNghiChieu":"15:07:25","tThoigianVaolamToi":null,"tThoigianNghiToi":null,"dNgayChamcong":"11-01-2021"}]